{
 "expires_on": "2018-11-06T05:00:00.000+00:00",
 "registered?": true,
 "domain": "lofter.com",
 "registrant_contacts": [
  {
   "id": null,
   "organization": "Hangzhou NetEase Leihuo Science & Technology Co., Ltd",
   "type": 1,
   "state": "Zhejiang",
   "name": "Domain Administrator",
   "url": null,
   "fax": "+86.57189853090",
   "updated_on": null,
   "email": "nsadmin@corp.netease.com",
   "city": "Hangzhou",
   "created_on": null,
   "zip": "310052",
   "address": "No. 599 Wangshang Road Binjiang District,",
   "country": null,
   "country_code": "CN",
   "phone": "+86.57189853091"
  }
 ],
 "technical_contacts": [
  {
   "id": null,
   "organization": "Hangzhou NetEase Leihuo Science & Technology Co., Ltd",
   "type": 3,
   "state": "Zhejiang",
   "name": "Domain Administrator",
   "url": null,
   "fax": "+86.57189853090",
   "updated_on": null,
   "email": "nsadmin@corp.netease.com",
   "city": "Hangzhou",
   "created_on": null,
   "zip": "310052",
   "address": "No. 599 Wangshang Road Binjiang District,",
   "country": null,
   "country_code": "CN",
   "phone": "+86.57189853091"
  }
 ],
 "disclaimer": "TERMS OF USE: You are not authorized to access or query our Whois database through the use of electronic processes that are high-volume and automated except as reasonably necessary to register domain names or modify existing registrations; the Data in VeriSign Global Registry Services' (\"VeriSign\") Whois database is provided by VeriSign for information purposes only, and to assist persons in obtaining information about or related to a domain name registration record. VeriSign does not guarantee its accuracy. By submitting a Whois query, you agree to abide by the following terms of use: You agree that you may use this Data only for lawful purposes and that under no circumstances will you use this Data to: (1) allow, enable, or otherwise support the transmission of mass unsolicited, commercial advertising or solicitations via e-mail, telephone, or facsimile; or (2) enable high volume, automated, electronic processes that apply to VeriSign (or its computer systems). The compilation, repackaging, dissemination or other use of this Data is expressly prohibited without the prior written consent of VeriSign. You agree not to use electronic processes that are automated and high-volume to access or query the Whois database except as reasonably necessary to register domain names or modify existing registrations. VeriSign reserves the right to restrict your access to the Whois database in its sole discretion to ensure operational stability.  VeriSign may restrict or terminate your access to the Whois database for failure to abide by these terms of use. VeriSign reserves the right to modify these terms at any time.",
 "updated_on": "2015-11-18T17:07:40.000+00:00",
 "created_on": "1997-11-07T05:00:00.000+00:00",
 "raw": "\nWhois Server Version 2.0\n\nDomain names in the .com and .net domains can now be registered\nwith many different competing registrars. Go to http://www.internic.net\nfor detailed information.\n\n   Domain Name: LOFTER.COM\n   Registrar: MARKMONITOR INC.\n   Sponsoring Registrar IANA ID: 292\n   Whois Server: whois.markmonitor.com\n   Referral URL: http://www.markmonitor.com\n   Name Server: LOFTERNS1.NETEASE.COM\n   Name Server: LOFTERNS2.NETEASE.COM\n   Name Server: LOFTERNS3.NETEASE.COM\n   Status: clientDeleteProhibited https://icann.org/epp#clientDeleteProhibited\n   Status: clientTransferProhibited https://icann.org/epp#clientTransferProhibited\n   Status: clientUpdateProhibited https://icann.org/epp#clientUpdateProhibited\n   Status: serverDeleteProhibited https://icann.org/epp#serverDeleteProhibited\n   Status: serverTransferProhibited https://icann.org/epp#serverTransferProhibited\n   Status: serverUpdateProhibited https://icann.org/epp#serverUpdateProhibited\n   Updated Date: 18-nov-2015\n   Creation Date: 07-nov-1997\n   Expiration Date: 06-nov-2018\n\n>>> Last update of whois database: Sun, 04 Sep 2016 05:07:36 GMT <<<\n\nFor more information on Whois status codes, please visit https://icann.org/epp\n\nNOTICE: The expiration date displayed in this record is the date the\nregistrar's sponsorship of the domain name registration in the registry is\ncurrently set to expire. This date does not necessarily reflect the expiration\ndate of the domain name registrant's agreement with the sponsoring\nregistrar.  Users may consult the sponsoring registrar's Whois database to\nview the registrar's reported date of expiration for this registration.\n\nTERMS OF USE: You are not authorized to access or query our Whois\ndatabase through the use of electronic processes that are high-volume and\nautomated except as reasonably necessary to register domain names or\nmodify existing registrations; the Data in VeriSign Global Registry\nServices' (\"VeriSign\") Whois database is provided by VeriSign for\ninformation purposes only, and to assist persons in obtaining information\nabout or related to a domain name registration record. VeriSign does not\nguarantee its accuracy. By submitting a Whois query, you agree to abide\nby the following terms of use: You agree that you may use this Data only\nfor lawful purposes and that under no circumstances will you use this Data\nto: (1) allow, enable, or otherwise support the transmission of mass\nunsolicited, commercial advertising or solicitations via e-mail, telephone,\nor facsimile; or (2) enable high volume, automated, electronic processes\nthat apply to VeriSign (or its computer systems). The compilation,\nrepackaging, dissemination or other use of this Data is expressly\nprohibited without the prior written consent of VeriSign. You agree not to\nuse electronic processes that are automated and high-volume to access or\nquery the Whois database except as reasonably necessary to register\ndomain names or modify existing registrations. VeriSign reserves the right\nto restrict your access to the Whois database in its sole discretion to ensure\noperational stability.  VeriSign may restrict or terminate your access to the\nWhois database for failure to abide by these terms of use. VeriSign\nreserves the right to modify these terms at any time.\n\nThe Registry database contains ONLY .COM, .NET, .EDU domains and\nRegistrars.\n\nDomain Name: lofter.com\nRegistry Domain ID: 612954_DOMAIN_COM-VRSN\nRegistrar WHOIS Server: whois.markmonitor.com\nRegistrar URL: http://www.markmonitor.com\nUpdated Date: 2015-11-18T09:07:40-0800\nCreation Date: 1997-11-06T21:00:00-0800\nRegistrar Registration Expiration Date: 2018-11-05T21:00:00-0800\nRegistrar: MarkMonitor, Inc.\nRegistrar IANA ID: 292\nRegistrar Abuse Contact Email: abusecomplaints@markmonitor.com\nRegistrar Abuse Contact Phone: +1.2083895740\nDomain Status: clientUpdateProhibited (https://www.icann.org/epp#clientUpdateProhibited)\nDomain Status: clientTransferProhibited (https://www.icann.org/epp#clientTransferProhibited)\nDomain Status: clientDeleteProhibited (https://www.icann.org/epp#clientDeleteProhibited)\nDomain Status: serverUpdateProhibited (https://www.icann.org/epp#serverUpdateProhibited)\nDomain Status: serverTransferProhibited (https://www.icann.org/epp#serverTransferProhibited)\nDomain Status: serverDeleteProhibited (https://www.icann.org/epp#serverDeleteProhibited)\nRegistry Registrant ID: \nRegistrant Name: Domain Administrator\nRegistrant Organization: Hangzhou NetEase Leihuo Science & Technology Co., Ltd\nRegistrant Street: No. 599 Wangshang Road Binjiang District, \nRegistrant City: Hangzhou\nRegistrant State/Province: Zhejiang\nRegistrant Postal Code: 310052\nRegistrant Country: CN\nRegistrant Phone: +86.57189853091\nRegistrant Phone Ext: \nRegistrant Fax: +86.57189853090\nRegistrant Fax Ext: \nRegistrant Email: nsadmin@corp.netease.com\nRegistry Admin ID: \nAdmin Name: Domain Administrator\nAdmin Organization: Hangzhou NetEase Leihuo Science & Technology Co., Ltd\nAdmin Street: No. 599 Wangshang Road Binjiang District, \nAdmin City: Hangzhou\nAdmin State/Province: Zhejiang\nAdmin Postal Code: 310052\nAdmin Country: CN\nAdmin Phone: +86.57189853091\nAdmin Phone Ext: \nAdmin Fax: +86.57189853090\nAdmin Fax Ext: \nAdmin Email: nsadmin@corp.netease.com\nRegistry Tech ID: \nTech Name: Domain Administrator\nTech Organization: Hangzhou NetEase Leihuo Science & Technology Co., Ltd\nTech Street: No. 599 Wangshang Road Binjiang District, \nTech City: Hangzhou\nTech State/Province: Zhejiang\nTech Postal Code: 310052\nTech Country: CN\nTech Phone: +86.57189853091\nTech Phone Ext: \nTech Fax: +86.57189853090\nTech Fax Ext: \nTech Email: nsadmin@corp.netease.com\nName Server: lofterns2.netease.com\nName Server: lofterns1.netease.com\nName Server: lofterns3.netease.com\nDNSSEC: unsigned\nURL of the ICANN WHOIS Data Problem Reporting System: http://wdprs.internic.net/\n>>> Last update of WHOIS database: 2016-09-03T22:07:55-0700 <<<\n\nThe Data in MarkMonitor.com's WHOIS database is provided by MarkMonitor.com for\ninformation purposes, and to assist persons in obtaining information about or\nrelated to a domain name registration record.  MarkMonitor.com does not guarantee\nits accuracy.  By submitting a WHOIS query, you agree that you will use this Data\nonly for lawful purposes and that, under no circumstances will you use this Data to:\n (1) allow, enable, or otherwise support the transmission of mass unsolicited,\n     commercial advertising or solicitations via e-mail (spam); or\n (2) enable high volume, automated, electronic processes that apply to\n     MarkMonitor.com (or its systems).\nMarkMonitor.com reserves the right to modify these terms at any time.\nBy submitting this query, you agree to abide by this policy.\n\nMarkMonitor is the Global Leader in Online Brand Protection.\n\nMarkMonitor Domain Management(TM)\nMarkMonitor Brand Protection(TM)\nMarkMonitor AntiPiracy(TM)\nMarkMonitor AntiFraud(TM)\nProfessional and Managed Services\n\nVisit MarkMonitor at http://www.markmonitor.com\nContact us at +1.8007459229\nIn Europe, at +44.02032062220\n\nFor more information on Whois status codes, please visit\n https://www.icann.org/resources/pages/epp-status-codes-2014-06-16-en\n\n",
 "available?": false,
 "status": "registered",
 "admin_contacts": [
  {
   "id": null,
   "organization": "Hangzhou NetEase Leihuo Science & Technology Co., Ltd",
   "type": 2,
   "state": "Zhejiang",
   "name": "Domain Administrator",
   "url": null,
   "fax": "+86.57189853090",
   "updated_on": null,
   "email": "nsadmin@corp.netease.com",
   "city": "Hangzhou",
   "created_on": null,
   "zip": "310052",
   "address": "No. 599 Wangshang Road Binjiang District,",
   "country": null,
   "country_code": "CN",
   "phone": "+86.57189853091"
  }
 ],
 "registrar": {
  "id": "292",
  "name": "MarkMonitor, Inc.",
  "organization": "MarkMonitor, Inc.",
  "url": "http://www.markmonitor.com"
 },
 "nameservers": [
  {
   "ipv6": null,
   "name": "lofterns2.netease.com",
   "ipv4": null
  },
  {
   "ipv6": null,
   "name": "lofterns1.netease.com",
   "ipv4": null
  },
  {
   "ipv6": null,
   "name": "lofterns3.netease.com",
   "ipv4": null
  }
 ],
 "domain_id": "612954_DOMAIN_COM-VRSN"
}
